.readthedocs.txt
MANIFEST.in
Readme.rst
requirements-dev.txt
requirements.txt
setup.py
bin/pub2
pub2/__init__.py
pub2/__meta__.py
pub2/file.py
pub2/pub2.py
pub2/reader.py
pub2/tests.py
pub2/writer.py
pub2.egg-info/PKG-INFO
pub2.egg-info/SOURCES.txt
pub2.egg-info/dependency_links.txt
pub2.egg-info/not-zip-safe
pub2.egg-info/requires.txt
pub2.egg-info/top_level.txt
pub2/skel/.mrbob.ini
pub2/skel/_data/.gitignore
pub2/skel/_includes/pub2-view.html
pub2/skel/_pages/pub2.html
pub2/skel/_pubs/first-post.tex
pub2/skel/_pubs/_assets/.gitignore
pub2/skel/_pubs/_assets/first-post/logo.png
pub2/skel/_pubs/_layouts/default.tex
pub2/skel/_pubs/_templates/blank.tex
pub2/skel/_pubs/_templates/citation.bib
pub2/skel/_pubs/_templates/view.html