Metadata-Version: 1.0
Name: pub2
Version: 0.1.6
Summary: Pub is a self-publishing framework.
Home-page: http://pub2.readthedocs.io
Author: Ian Dennis Miller
Author-email: iandennismiller@gmail.com
License: MIT
Platform: UNKNOWN
